monalisten/__init__.py
monalisten/_core.py
monalisten/_errors.py
monalisten/_event_namespace.py
monalisten/_namespace.py
monalisten/_sse.py
monalisten/events.py
monalisten/py.typed
monalisten-0.3.2.dist-info/WHEEL
monalisten-0.3.2.dist-info/METADATA
monalisten-0.3.2.dist-info/RECORD
