Metadata-Version: 2.4
Name: monalisten
Version: 0.3.2
Summary: Monalisten is an async library for handling GitHub webhook events in an easy way
Author: trag1c
Author-email: trag1c <dev@jakubr.me>
License-Expression: MIT
Requires-Dist: githubkit>=0.14.0
Requires-Dist: httpx>=0.28.1
Requires-Dist: httpx-sse>=0.4.3
Requires-Python: >=3.10
Project-URL: repository, https://github.com/trag1c/monalisten
